vcf2xlsx/__init__.py
vcf2xlsx/main.py
vcf2xlsx-0.2.0.dist-info/LICENSE
vcf2xlsx-0.2.0.dist-info/METADATA
vcf2xlsx-0.2.0.dist-info/WHEEL
vcf2xlsx-0.2.0.dist-info/entry_points.txt
vcf2xlsx-0.2.0.dist-info/RECORD
